setup.py
src/iot_jumpway_mqtt_serial/__init__.py
src/iot_jumpway_mqtt_serial/device.py
src/iot_jumpway_mqtt_serial.egg-info/PKG-INFO
src/iot_jumpway_mqtt_serial.egg-info/SOURCES.txt
src/iot_jumpway_mqtt_serial.egg-info/dependency_links.txt
src/iot_jumpway_mqtt_serial.egg-info/requires.txt
src/iot_jumpway_mqtt_serial.egg-info/top_level.txt