Metadata-Version: 1.0
Name: iot-jumpway-mqtt-serial
Version: 0.0.1
Summary: IoT JumpWay Python MQTT Serial Client
Home-page: https://github.com/TechBubbleTechnologies/IoT-JumpWay-Python-MQTT-Serial-Client
Author: Adam Milton-Barker
Author-email: adammiltonbarker@gmail.com
License: BSD
Platform: UNKNOWN
